jmbg_validator/__init__.py
jmbg_validator/exceptions.py
jmbg_validator/main.py
jmbg_validator/matrices.py
jmbg_validator/output.py
JMBG_Validator-1.0.2.dist-info/LICENSE.md
JMBG_Validator-1.0.2.dist-info/METADATA
JMBG_Validator-1.0.2.dist-info/WHEEL
JMBG_Validator-1.0.2.dist-info/entry_points.txt
JMBG_Validator-1.0.2.dist-info/top_level.txt
JMBG_Validator-1.0.2.dist-info/RECORD
